frantic/__init__.py
frantic/base.py
frantic/exceptions.py
frantic/frantic.py
frantic/version.py
frantic-0.1.3.dist-info/LICENSE
frantic-0.1.3.dist-info/WHEEL
frantic-0.1.3.dist-info/METADATA
frantic-0.1.3.dist-info/RECORD
