Metadata-Version: 2.1
Name: frantic
Version: 0.1.3
Summary: Firestore with Pydantic models integration
Home-page: https://github.com/tomasvotava/frantic
License: MIT
Author: Tomas Votava
Author-email: info@tomasvotava.eu
Requires-Python: >=3.10,<4.0
Classifier: License :: OSI Approved :: MIT License
Classifier: Programming Language :: Python :: 3
Classifier: Programming Language :: Python :: 3.10
Requires-Dist: google-cloud-firestore (>=2.6.0,<3.0.0)
Requires-Dist: pydantic (>=1.9.1,<2.0.0)
Project-URL: Documentation, https://tomasvotava.github.io/frantic
Project-URL: Repository, https://github.com/tomasvotava/frantic
